defpkg/__init__.py
defpkg-2024.1.0.dist-info/LICENSE
defpkg-2024.1.0.dist-info/METADATA
defpkg-2024.1.0.dist-info/WHEEL
defpkg-2024.1.0.dist-info/top_level.txt
defpkg-2024.1.0.dist-info/RECORD
