Metadata-Version: 2.1
Name: defpkg
Version: 2024.1.0
Summary: a simple library for creating interesting things in your code
Author-email: risknu <risknu.go@gmail.com>
Project-URL: Homepage, https://github.com/risknu/defpkg
Project-URL: Issues, https://github.com/risknu/defpkg/issues
Classifier: Programming Language :: Python :: 3
Classifier: License :: OSI Approved :: Apache Software License
Classifier: Operating System :: OS Independent
Requires-Python: >=3.11
License-File: LICENSE
